{"104FW21":{
  "Admin NF" : "GER",
  "Administering NF" : "GER",
  "Birth_Name" : "BACCORD",
  "Block_automatic_NF" : "No",
  "Breed" : "Oldenburger Springpferd",
  "Breeders_name" : "Lueckmann, Alois",
  "Castrated_Sterilized" : "Yes",
  "Chip_ID" : "276020000238134",
  "Color_Code" : "Bay",
  "Commercial_prefix_or_suffix" : "",
  "Competition" : {
    "01-04-2014,Arezzo - Toscana Tour" : {
      "Article" : "238.1.1a",
      "Athlete" : "Dieter HAUCK (GER)",
      "Competition" : "Table A",
      "Event" : "CSIYH1*",
      "FEIID" : "10103664",
      "Obstheigh" : "115",
      "Pos" : "1",
      "Score" : "0",
      "Show" : "Arezzo - Toscana Tour",
      "StartDate" : "01/04/2014"
    },
    "01-07-2018,Knokke" : {
      "Article" : "274.5.3",
      "Athlete" : "Gerrit NIEBERG (GER)",
      "Competition" : "Two Phases",
      "Event" : "CSI3*",
      "FEIID" : "10046659",
      "Obstheigh" : "145",
      "Pos" : "8",
      "Score" : "0/55.23/0/35.98",
      "Show" : "Knokke",
      "StartDate" : "01/07/2018"
    },
    "01-09-2016,Humlikon" : {
      "Article" : "238.2.1a",
      "Athlete" : "Gerrit NIEBERG (GER)",
      "Competition" : "Int. Jumping Competition Preis der CayZe...",
      "Event" : "CSI3*",
      "FEIID" : "10046659",
      "Obstheigh" : "130",
      "Pos" : "17",
      "Score" : "0/64.33",
      "Show" : "Humlikon",
      "StartDate" : "01/09/2016"
    },
    "02-03-2017,Dortmund" : {
      "Article" : "238.2.1a",
      "Athlete" : "Gerrit NIEBERG (GER)",
      "Competition" : "Table A",
      "Event" : "CSIYH1* incl. 8yo",
      "FEIID" : "10046659",
      "Obstheigh" : "140-145",
      "Pos" : "17",
      "Score" : "0/65.45",
      "Show" : "Dortmund",
      "StartDate" : "02/03/2017"
    },
    "02-04-2014,Arezzo - Toscana Tour" : {
      "Article" : "238.1.1a",
      "Athlete" : "Dieter HAUCK (GER)",
      "Competition" : "Table A",
      "Event" : "CSIYH1*",
      "FEIID" : "10103664",
      "Obstheigh" : "115",
      "Pos" : "1",
      "Score" : "0",
      "Show" : "Arezzo - Toscana Tour",
      "StartDate" : "02/04/2014"
    },
    "02-08-2015,Donaueschingen-Immenhöfe" : {
      "Article" : "274.5.6",
      "Athlete" : "Gerrit NIEBERG (GER)",
      "Competition" : "Two Phases",
      "Event" : "CSIYH1*",
      "FEIID" : "10046659",
      "Obstheigh" : "135",
      "Pos" : "7",
      "Score" : "0/53.95/0/36.43",
      "Show" : "Donaueschingen-Immenhöfe",
      "StartDate" : "02/08/2015"
    },
    "02-09-2016,Humlikon" : {
      "Article" : "274.5.3",
      "Athlete" : "Gerrit NIEBERG (GER)",
      "Competition" : "Int. Jumping Competition Preis von Irene...",
      "Event" : "CSI3*",
      "FEIID" : "10046659",
      "Obstheigh" : "135",
      "Pos" : "14",
      "Score" : "0/30.36",
      "Show" : "Humlikon",
      "StartDate" : "02/09/2016"
    },
    "03-04-2014,Arezzo - Toscana Tour" : {
      "Article" : "274.5.1",
      "Athlete" : "Dieter HAUCK (GER)",
      "Competition" : "Two Phases",
      "Event" : "CSIYH1*",
      "FEIID" : "10103664",
      "Obstheigh" : "115",
      "Pos" : "1",
      "Score" : "0/0",
      "Show" : "Arezzo - Toscana Tour",
      "StartDate" : "03/04/2014"
    },
    "03-09-2016,Humlikon" : {
      "Article" : "238.2.1a",
      "Athlete" : "Gerrit NIEBERG (GER)",
      "Competition" : "Int. Jumping Competition Preis der Scara...",
      "Event" : "CSI3*",
      "FEIID" : "10046659",
      "Obstheigh" : "130",
      "Pos" : "9",
      "Score" : "0/62.95",
      "Show" : "Humlikon",
      "StartDate" : "03/09/2016"
    },
    "03-11-2017,Oldenburg" : {
      "Article" : "238.2.1a",
      "Athlete" : "Gerrit NIEBERG (GER)",
      "Competition" : "Table A",
      "Event" : "CSI3*",
      "FEIID" : "10046659",
      "Obstheigh" : "140",
      "Pos" : "77",
      "Score" : "5/64.79",
      "Show" : "Oldenburg",
      "StartDate" : "03/11/2017"
    },
    "04-03-2017,Dortmund" : {
      "Article" : "238.2.2a",
      "Athlete" : "Gerrit NIEBERG (GER)",
      "Competition" : "Table A",
      "Event" : "CSIYH1* incl. 8yo",
      "FEIID" : "10046659",
      "Obstheigh" : "145-150",
      "Pos" : "12",
      "Score" : "4/63.40",
      "Show" : "Dortmund",
      "StartDate" : "04/03/2017"
    },
    "04-08-2016,Verden" : {
      "Article" : "238.2.1a",
      "Athlete" : "Gerrit NIEBERG (GER)",
      "Competition" : "Table A",
      "Event" : "CSIYH1* incl. 8yo",
      "FEIID" : "10046659",
      "Obstheigh" : "135",
      "Pos" : "28",
      "Score" : "1/72.05",
      "Show" : "Verden",
      "StartDate" : "04/08/2016"
    },
    "04-11-2017,Oldenburg" : {
      "Article" : "269a",
      "Athlete" : "Gerrit NIEBERG (GER)",
      "Competition" : "Accumulator",
      "Event" : "CSI3*",
      "FEIID" : "10046659",
      "Obstheigh" : "140",
      "Pos" : "22",
      "Score" : "25/47.83",
      "Show" : "Oldenburg",
      "StartDate" : "04/11/2017"
    },
    "05-04-2016,Cagnes-sur-Mer" : {
      "Article" : "238.1.1a",
      "Athlete" : "Gerrit NIEBERG (GER)",
      "Competition" : "Table A - T A, one round not atc",
      "Event" : "CSIYH1*",
      "FEIID" : "10046659",
      "Obstheigh" : "125",
      "Pos" : "1",
      "Score" : "0/79.88",
      "Show" : "Cagnes-sur-Mer",
      "StartDate" : "05/04/2016"
    },
    "05-05-2018                                08_00,Mannheim" : {
      "Article" : "238.2.1a",
      "Athlete" : "Gerrit NIEBERG (GER)",
      "Competition" : "Table A",
      "Event" : "CSI3*",
      "FEIID" : "10046659",
      "Obstheigh" : "140",
      "Pos" : "24",
      "Score" : "1/64.65",
      "Show" : "Mannheim",
      "StartDate" : "05/05/2018                                08:00"
    },
    "05-08-2016,Verden" : {
      "Article" : "238.2.1a",
      "Athlete" : "Gerrit NIEBERG (GER)",
      "Competition" : "Table A",
      "Event" : "CSIYH1* incl. 8yo",
      "FEIID" : "10046659",
      "Obstheigh" : "140",
      "Pos" : "28",
      "Score" : "1/84.45",
      "Show" : "Verden",
      "StartDate" : "05/08/2016"
    },
    "06-04-2016,Cagnes-sur-Mer" : {
      "Article" : "238.2.1a",
      "Athlete" : "Gerrit NIEBERG (GER)",
      "Competition" : "Table A - T A, one round atc",
      "Event" : "CSIYH1*",
      "FEIID" : "10046659",
      "Obstheigh" : "130",
      "Pos" : "24",
      "Score" : "0/81.00",
      "Show" : "Cagnes-sur-Mer",
      "StartDate" : "06/04/2016"
    },
    "06-04-2017,Kronenberg" : {
      "Article" : "238.2.1a",
      "Athlete" : "Gerrit NIEBERG (GER)",
      "Competition" : "Table A",
      "Event" : "CSI2*",
      "FEIID" : "10046659",
      "Obstheigh" : "140",
      "Pos" : "15",
      "Score" : "0/63.63",
      "Show" : "Kronenberg",
      "StartDate" : "06/04/2017"
    },
    "06-05-2017,Mannheim" : {
      "Article" : "238.2.1a",
      "Athlete" : "Gerrit NIEBERG (GER)",
      "Competition" : "Table A",
      "Event" : "CSIYH1* incl. 8yo",
      "FEIID" : "10046659",
      "Obstheigh" : "135",
      "Pos" : "16",
      "Score" : "0/67.72",
      "Show" : "Mannheim",
      "StartDate" : "06/05/2017"
    },
    "06-08-2016,Verden" : {
      "Article" : "274.5.6",
      "Athlete" : "Gerrit NIEBERG (GER)",
      "Competition" : "Two Phases",
      "Event" : "CSIYH1* incl. 8yo",
      "FEIID" : "10046659",
      "Obstheigh" : "140",
      "Pos" : "22",
      "Score" : "4/46.65/4/37.83",
      "Show" : "Verden",
      "StartDate" : "06/08/2016"
    },
    "06-10-2016,Riesenbeck" : {
      "Article" : "238.2.1a",
      "Athlete" : "Gerrit NIEBERG (GER)",
      "Competition" : "Table A",
      "Event" : "CSIYH1*",
      "FEIID" : "10046659",
      "Obstheigh" : "135",
      "Pos" : "45",
      "Score" : "4/7527.00",
      "Show" : "Riesenbeck",
      "StartDate" : "06/10/2016"
    },
    "07-04-2016,Cagnes-sur-Mer" : {
      "Article" : "238.2.2a",
      "Athlete" : "Gerrit NIEBERG (GER)",
      "Competition" : "Table A - T A, one round atc with one ju...",
      "Event" : "CSIYH1*",
      "FEIID" : "10046659",
      "Obstheigh" : "135",
      "Pos" : "34",
      "Score" : "4/89.68",
      "Show" : "Cagnes-sur-Mer",
      "StartDate" : "07/04/2016"
    },
    "07-04-2017,Kronenberg" : {
      "Article" : "274.5.3",
      "Athlete" : "Gerrit NIEBERG (GER)",
      "Competition" : "Two Phases",
      "Event" : "CSI2*",
      "FEIID" : "10046659",
      "Obstheigh" : "140",
      "Pos" : "56",
      "Score" : "4/57.02",
      "Show" : "Kronenberg",
      "StartDate" : "07/04/2017"
    },
    "07-05-2018                                09_00,Mannheim" : {
      "Article" : "263",
      "Athlete" : "Gerrit NIEBERG (GER)",
      "Competition" : "Table C",
      "Event" : "CSI3*",
      "FEIID" : "10046659",
      "Obstheigh" : "145",
      "Pos" : "20",
      "Score" : "75.36",
      "Show" : "Mannheim",
      "StartDate" : "07/05/2018                                09:00"
    },
    "07-09-2018                                13_25,Paderborn" : {
      "Article" : "238.2.1a",
      "Athlete" : "Lars NIEBERG (GER)",
      "Competition" : "Table A",
      "Event" : "CSI3*",
      "FEIID" : "10000416",
      "Obstheigh" : "140",
      "Pos" : "7",
      "Score" : "0/61.12",
      "Show" : "Paderborn",
      "StartDate" : "07/09/2018                                13:25"
    },
    "07-10-2016,Riesenbeck" : {
      "Article" : "238.2.1a",
      "Athlete" : "Gerrit NIEBERG (GER)",
      "Competition" : "Table A",
      "Event" : "CSIYH1*",
      "FEIID" : "10046659",
      "Obstheigh" : "135",
      "Pos" : "47",
      "Score" : "8/8036.00",
      "Show" : "Riesenbeck",
      "StartDate" : "07/10/2016"
    },
    "08-04-2017,Kronenberg" : {
      "Article" : "238.2.2a",
      "Athlete" : "Gerrit NIEBERG (GER)",
      "Competition" : "Table A",
      "Event" : "CSI2*",
      "FEIID" : "10046659",
      "Obstheigh" : "140",
      "Pos" : "50",
      "Score" : "12/93.10",
      "Show" : "Kronenberg",
      "StartDate" : "08/04/2017"
    },
    "08-05-2017,Mannheim" : {
      "Article" : "238.2.1a",
      "Athlete" : "Gerrit NIEBERG (GER)",
      "Competition" : "Table A",
      "Event" : "CSIYH1* incl. 8yo",
      "FEIID" : "10046659",
      "Obstheigh" : "140",
      "Pos" : "18",
      "Score" : "0/67.88",
      "Show" : "Mannheim",
      "StartDate" : "08/05/2017"
    },
    "08-05-2018                                08_00,Mannheim" : {
      "Article" : "238.2.1a",
      "Athlete" : "Gerrit NIEBERG (GER)",
      "Competition" : "Table A",
      "Event" : "CSI3*",
      "FEIID" : "10046659",
      "Obstheigh" : "140",
      "Pos" : "13",
      "Score" : "0/62.34",
      "Show" : "Mannheim",
      "StartDate" : "08/05/2018                                08:00"
    },
    "08-09-2018                                10_50,Paderborn" : {
      "Article" : "269a",
      "Athlete" : "Lars NIEBERG (GER)",
      "Competition" : "Accumulator",
      "Event" : "CSI3*",
      "FEIID" : "10000416",
      "Obstheigh" : "140",
      "Pos" : "4",
      "Score" : "65/50.25",
      "Show" : "Paderborn",
      "StartDate" : "08/09/2018                                10:50"
    },
    "09-05-2016,Mannheim" : {
      "Article" : "238.2.1a",
      "Athlete" : "Gerrit NIEBERG (GER)",
      "Competition" : "Table A",
      "Event" : "CSIYH1* incl. 8yo",
      "FEIID" : "10046659",
      "Obstheigh" : "140-145",
      "Pos" : "17",
      "Score" : "0/76.28",
      "Show" : "Mannheim",
      "StartDate" : "09/05/2016"
    },
    "09-05-2017,Mannheim" : {
      "Article" : "238.2.2a",
      "Athlete" : "Gerrit NIEBERG (GER)",
      "Competition" : "Table A",
      "Event" : "CSIYH1* incl. 8yo",
      "FEIID" : "10046659",
      "Obstheigh" : "145",
      "Pos" : "14",
      "Score" : "0/4/41.13",
      "Show" : "Mannheim",
      "StartDate" : "09/05/2017"
    },
    "09-09-2018                                10_10,Paderborn" : {
      "Article" : "274.5.3",
      "Athlete" : "Lars NIEBERG (GER)",
      "Competition" : "Two Phases",
      "Event" : "CSI3*",
      "FEIID" : "10000416",
      "Obstheigh" : "145",
      "Pos" : "35",
      "Score" : "4/56.81",
      "Show" : "Paderborn",
      "StartDate" : "09/09/2018                                10:10"
    },
    "09-10-2016,Riesenbeck" : {
      "Article" : "274.5.3",
      "Athlete" : "Gerrit NIEBERG (GER)",
      "Competition" : "Two Phases",
      "Event" : "CSIYH1*",
      "FEIID" : "10046659",
      "Obstheigh" : "140",
      "Pos" : "4",
      "Score" : "0/0/26.06",
      "Show" : "Riesenbeck",
      "StartDate" : "09/10/2016"
    },
    "10-05-2016,Mannheim" : {
      "Article" : "238.2.2a",
      "Athlete" : "Gerrit NIEBERG (GER)",
      "Competition" : "Table A",
      "Event" : "CSIYH1* incl. 8yo",
      "FEIID" : "10046659",
      "Obstheigh" : "140-145",
      "Pos" : "9",
      "Score" : "0/0/48.24",
      "Show" : "Mannheim",
      "StartDate" : "10/05/2016"
    },
    "10-11-2016,Opglabbeek" : {
      "Article" : "274.5.3",
      "Athlete" : "Gerrit NIEBERG (GER)",
      "Competition" : "Two Phases",
      "Event" : "CSI3*",
      "FEIID" : "10046659",
      "Obstheigh" : "140",
      "Pos" : "15",
      "Score" : "0/0/32.89",
      "Show" : "Opglabbeek",
      "StartDate" : "10/11/2016"
    },
    "10-11-2017,München" : {
      "Article" : "238.2.1a",
      "Athlete" : "Gerrit NIEBERG (GER)",
      "Competition" : "Table A",
      "Event" : "CSIYH1* incl. 8yo",
      "FEIID" : "10046659",
      "Obstheigh" : "135",
      "Pos" : "23",
      "Score" : "0/62.66",
      "Show" : "München",
      "StartDate" : "10/11/2017"
    },
    "11-08-2016,Allersehl" : {
      "Article" : "238.2.1a",
      "Athlete" : "Gerrit NIEBERG (GER)",
      "Competition" : "Table A",
      "Event" : "CSIYH1* incl. 8yo",
      "FEIID" : "10046659",
      "Obstheigh" : "130-135",
      "Pos" : "22",
      "Score" : "0/64.17",
      "Show" : "Allersehl",
      "StartDate" : "11/08/2016"
    },
    "11-08-2017,Münster" : {
      "Article" : "238.2.1a",
      "Athlete" : "Gerrit NIEBERG (GER)",
      "Competition" : "Table A",
      "Event" : "CSIYH1* incl. 8yo",
      "FEIID" : "10046659",
      "Obstheigh" : "140",
      "Pos" : "6",
      "Score" : "0/67.09",
      "Show" : "Münster",
      "StartDate" : "11/08/2017"
    },
    "11-11-2016,Opglabbeek" : {
      "Article" : "238.2.2a",
      "Athlete" : "Gerrit NIEBERG (GER)",
      "Competition" : "Table A",
      "Event" : "CSI3*",
      "FEIID" : "10046659",
      "Obstheigh" : "140",
      "Pos" : "28",
      "Score" : "4/67.05",
      "Show" : "Opglabbeek",
      "StartDate" : "11/11/2016"
    },
    "11-11-2017,München" : {
      "Article" : "238.2.1a",
      "Athlete" : "Gerrit NIEBERG (GER)",
      "Competition" : "Table A",
      "Event" : "CSIYH1* incl. 8yo",
      "FEIID" : "10046659",
      "Obstheigh" : "140",
      "Pos" : "18",
      "Score" : "0/61.05",
      "Show" : "München",
      "StartDate" : "11/11/2017"
    },
    "12-08-2017,Münster" : {
      "Article" : "238.2.2a",
      "Athlete" : "Gerrit NIEBERG (GER)",
      "Competition" : "Table A",
      "Event" : "CSIYH1* incl. 8yo",
      "FEIID" : "10046659",
      "Obstheigh" : "140-145",
      "Pos" : "6",
      "Score" : "0/ret",
      "Show" : "Münster",
      "StartDate" : "12/08/2017"
    },
    "12-11-2017,München" : {
      "Article" : "274.5.3",
      "Athlete" : "Gerrit NIEBERG (GER)",
      "Competition" : "Two Phases",
      "Event" : "CSIYH1* incl. 8yo",
      "FEIID" : "10046659",
      "Obstheigh" : "140",
      "Pos" : "16",
      "Score" : "4/45.77",
      "Show" : "München",
      "StartDate" : "12/11/2017"
    },
    "13-08-2016,Allersehl" : {
      "Article" : "274.5.6",
      "Athlete" : "Gerrit NIEBERG (GER)",
      "Competition" : "Two Phases",
      "Event" : "CSIYH1* incl. 8yo",
      "FEIID" : "10046659",
      "Obstheigh" : "135-140",
      "Pos" : "55",
      "Score" : "0/56.97/EL",
      "Show" : "Allersehl",
      "StartDate" : "13/08/2016"
    },
    "13-11-2016,Opglabbeek" : {
      "Article" : "238.2.2a",
      "Athlete" : "Gerrit NIEBERG (GER)",
      "Competition" : "Table A",
      "Event" : "CSI3*",
      "FEIID" : "10046659",
      "Obstheigh" : "145",
      "Pos" : "37",
      "Score" : "5/78.49",
      "Show" : "Opglabbeek",
      "StartDate" : "13/11/2016"
    },
    "14-01-2016,Drachten" : {
      "Article" : "274.5.3",
      "Athlete" : "Gerrit NIEBERG (GER)",
      "Competition" : "F.C. NIENHUIS WEGBEVEILIGING PRIJS",
      "Event" : "CSI1*",
      "FEIID" : "10046659",
      "Obstheigh" : "120",
      "Pos" : "17",
      "Score" : "0/0.00/0/39.14",
      "Show" : "Drachten",
      "StartDate" : "14/01/2016"
    },
    "14-08-2015,Roosendaal" : {
      "Article" : "274.5.3",
      "Athlete" : "Gerrit NIEBERG (GER)",
      "Competition" : "Two Phases",
      "Event" : "CSIYH1*",
      "FEIID" : "10046659",
      "Obstheigh" : "130-135",
      "Pos" : "13",
      "Score" : "0/0/37.61",
      "Show" : "Roosendaal",
      "StartDate" : "14/08/2015"
    },
    "14-08-2016,Allersehl" : {
      "Article" : "238.2.2a",
      "Athlete" : "Gerrit NIEBERG (GER)",
      "Competition" : "Table A",
      "Event" : "CSIYH1* incl. 8yo",
      "FEIID" : "10046659",
      "Obstheigh" : "140-145",
      "Pos" : "26",
      "Score" : "4/75.82",
      "Show" : "Allersehl",
      "StartDate" : "14/08/2016"
    },
    "14-12-2018,Frankfurt" : {
      "Article" : "238.2.1a",
      "Athlete" : "Gerrit NIEBERG (GER)",
      "Competition" : "Table A",
      "Event" : "CSI3*",
      "FEIID" : "10046659",
      "Obstheigh" : "140",
      "Pos" : "49",
      "Score" : "8/71.64",
      "Show" : "Frankfurt",
      "StartDate" : "14/12/2018"
    },
    "15-01-2016,Drachten" : {
      "Article" : "274.5.3",
      "Athlete" : "Gerrit NIEBERG (GER)",
      "Competition" : "F.C. NIENHUIS WEGBEVEILIGING PRIJS",
      "Event" : "CSI1*",
      "FEIID" : "10046659",
      "Obstheigh" : "130",
      "Pos" : "44",
      "Score" : "0/0.00/4/30.70",
      "Show" : "Drachten",
      "StartDate" : "15/01/2016"
    },
    "15-08-2015,Roosendaal" : {
      "Article" : "238.2.1a",
      "Athlete" : "Gerrit NIEBERG (GER)",
      "Competition" : "Table A",
      "Event" : "CSIYH1*",
      "FEIID" : "10046659",
      "Obstheigh" : "130-135",
      "Pos" : "25",
      "Score" : "4/70.92",
      "Show" : "Roosendaal",
      "StartDate" : "15/08/2015"
    },
    "15-11-2018,Stuttgart" : {
      "Article" : "274.5.6",
      "Athlete" : "Gerrit NIEBERG (GER)",
      "Competition" : "Two Phases",
      "Event" : "CSI5*-W",
      "FEIID" : "10046659",
      "Obstheigh" : "145",
      "Pos" : "23",
      "Score" : "0/1/22.72",
      "Show" : "Stuttgart",
      "StartDate" : "15/11/2018"
    },
    "15-12-2017,Frankfurt" : {
      "Article" : "274.5.6",
      "Athlete" : "Gerrit NIEBERG (GER)",
      "Competition" : "Two Phases",
      "Event" : "CSIYH1* incl. 8yo",
      "FEIID" : "10046659",
      "Obstheigh" : "135-140",
      "Pos" : "33",
      "Score" : "4/32.00/4/33.57",
      "Show" : "Frankfurt",
      "StartDate" : "15/12/2017"
    },
    "15-12-2018,Frankfurt" : {
      "Article" : "238.2.2a",
      "Athlete" : "Gerrit NIEBERG (GER)",
      "Competition" : "Table A",
      "Event" : "CSI3*",
      "FEIID" : "10046659",
      "Obstheigh" : "145",
      "Pos" : "6",
      "Score" : "0/0/41.35",
      "Show" : "Frankfurt",
      "StartDate" : "15/12/2018"
    },
    "16-01-2016,Drachten" : {
      "Article" : "238.2.2a",
      "Athlete" : "Gerrit NIEBERG (GER)",
      "Competition" : "F.C. NIENHUIS WEGBEVEILIGING PRIJS",
      "Event" : "CSI1*",
      "FEIID" : "10046659",
      "Obstheigh" : "130",
      "Pos" : "23",
      "Score" : "1/69.56",
      "Show" : "Drachten",
      "StartDate" : "16/01/2016"
    },
    "16-08-2015,Roosendaal" : {
      "Article" : "238.2.2a",
      "Athlete" : "Gerrit NIEBERG (GER)",
      "Competition" : "Table A",
      "Event" : "CSIYH1*",
      "FEIID" : "10046659",
      "Obstheigh" : "130-135",
      "Pos" : "10",
      "Score" : "0/12/49.54",
      "Show" : "Roosendaal",
      "StartDate" : "16/08/2015"
    },
    "16-09-2016,Donaueschingen" : {
      "Article" : "238.2.1a",
      "Athlete" : "Gerrit NIEBERG (GER)",
      "Competition" : "Table A",
      "Event" : "CSIYH1*",
      "FEIID" : "10046659",
      "Obstheigh" : "135",
      "Pos" : "27",
      "Score" : "4/68.15",
      "Show" : "Donaueschingen",
      "StartDate" : "16/09/2016"
    },
    "16-11-2018,Stuttgart" : {
      "Article" : "238.2.1a",
      "Athlete" : "Gerrit NIEBERG (GER)",
      "Competition" : "Table A",
      "Event" : "CSI5*-W",
      "FEIID" : "10046659",
      "Obstheigh" : "145",
      "Pos" : "19",
      "Score" : "0/60.51",
      "Show" : "Stuttgart",
      "StartDate" : "16/11/2018"
    },
    "16-12-2017,Frankfurt" : {
      "Article" : "238.2.1a",
      "Athlete" : "Gerrit NIEBERG (GER)",
      "Competition" : "Table A",
      "Event" : "CSIYH1* incl. 8yo",
      "FEIID" : "10046659",
      "Obstheigh" : "140-145",
      "Pos" : "6",
      "Score" : "0/59.22",
      "Show" : "Frankfurt",
      "StartDate" : "16/12/2017"
    },
    "17-09-2016,Donaueschingen" : {
      "Article" : "238.2.2a",
      "Athlete" : "Gerrit NIEBERG (GER)",
      "Competition" : "Table A",
      "Event" : "CSIYH1*",
      "FEIID" : "10046659",
      "Obstheigh" : "140",
      "Pos" : "22",
      "Score" : "8/84.92",
      "Show" : "Donaueschingen",
      "StartDate" : "17/09/2016"
    },
    "17-11-2016,Kronenberg" : {
      "Article" : "274.5.3",
      "Athlete" : "Gerrit NIEBERG (GER)",
      "Competition" : "Two Phases",
      "Event" : "CSIYH1*",
      "FEIID" : "10046659",
      "Obstheigh" : "130-135",
      "Pos" : "14",
      "Score" : "0/51.43/0/29.98",
      "Show" : "Kronenberg",
      "StartDate" : "17/11/2016"
    },
    "17-12-2017,Frankfurt" : {
      "Article" : "274.5.3",
      "Athlete" : "Gerrit NIEBERG (GER)",
      "Competition" : "Two Phases",
      "Event" : "CSIYH1* incl. 8yo",
      "FEIID" : "10046659",
      "Obstheigh" : "140-145",
      "Pos" : "18",
      "Score" : "4/42.23",
      "Show" : "Frankfurt",
      "StartDate" : "17/12/2017"
    },
    "18-03-2016,Kronenberg" : {
      "Article" : "274.5.3",
      "Athlete" : "Gerrit NIEBERG (GER)",
      "Competition" : "Two Phases",
      "Event" : "CSIYH1*",
      "FEIID" : "10046659",
      "Obstheigh" : "130-135",
      "Pos" : "16",
      "Score" : "0/56.23/0/33.34",
      "Show" : "Kronenberg",
      "StartDate" : "18/03/2016"
    },
    "18-11-2016,Kronenberg" : {
      "Article" : "238.2.1a",
      "Athlete" : "Gerrit NIEBERG (GER)",
      "Competition" : "Table A",
      "Event" : "CSIYH1*",
      "FEIID" : "10046659",
      "Obstheigh" : "130-135",
      "Pos" : "57",
      "Score" : "8/78.63",
      "Show" : "Kronenberg",
      "StartDate" : "18/11/2016"
    },
    "19-03-2016,Kronenberg" : {
      "Article" : "238.2.1a",
      "Athlete" : "Gerrit NIEBERG (GER)",
      "Competition" : "Table A",
      "Event" : "CSIYH1*",
      "FEIID" : "10046659",
      "Obstheigh" : "130-135",
      "Pos" : "12",
      "Score" : "0/69.41",
      "Show" : "Kronenberg",
      "StartDate" : "19/03/2016"
    },
    "19-11-2016,Kronenberg" : {
      "Article" : "238.2.2a",
      "Athlete" : "Gerrit NIEBERG (GER)",
      "Competition" : "Table A",
      "Event" : "CSIYH1*",
      "FEIID" : "10046659",
      "Obstheigh" : "130-135",
      "Pos" : "EL",
      "Score" : "R1 EL",
      "Show" : "Kronenberg",
      "StartDate" : "19/11/2016"
    },
    "20-03-2016,Kronenberg" : {
      "Article" : "238.2.2a",
      "Athlete" : "Gerrit NIEBERG (GER)",
      "Competition" : "Table A",
      "Event" : "CSIYH1*",
      "FEIID" : "10046659",
      "Obstheigh" : "130-135",
      "Pos" : "10",
      "Score" : "0/0/34.86",
      "Show" : "Kronenberg",
      "StartDate" : "20/03/2016"
    },
    "20-05-2016,Nörten-Hardenberg" : {
      "Article" : "238.2.1a",
      "Athlete" : "Gerrit NIEBERG (GER)",
      "Competition" : "Table A",
      "Event" : "CSIYH1*",
      "FEIID" : "10046659",
      "Obstheigh" : "135",
      "Pos" : "17",
      "Score" : "0/63.19",
      "Show" : "Nörten-Hardenberg",
      "StartDate" : "20/05/2016"
    },
    "20-10-2017,Kronenberg" : {
      "Article" : "274.5.3",
      "Athlete" : "Lars NIEBERG (GER)",
      "Competition" : "Two Phases",
      "Event" : "CSI2*",
      "FEIID" : "10000416",
      "Obstheigh" : "135",
      "Pos" : "30",
      "Score" : "0/51.43/0/36.85",
      "Show" : "Kronenberg",
      "StartDate" : "20/10/2017"
    },
    "21-01-2016,Schwerin" : {
      "Article" : "238.2.1a",
      "Athlete" : "Gerrit NIEBERG (GER)",
      "Competition" : "Table A",
      "Event" : "CSI1*",
      "FEIID" : "10046659",
      "Obstheigh" : "130",
      "Pos" : "28",
      "Score" : "0/54.51",
      "Show" : "Schwerin",
      "StartDate" : "21/01/2016"
    },
    "21-05-2016,Nörten-Hardenberg" : {
      "Article" : "238.2.2a",
      "Athlete" : "Gerrit NIEBERG (GER)",
      "Competition" : "Table A",
      "Event" : "CSIYH1*",
      "FEIID" : "10046659",
      "Obstheigh" : "140",
      "Pos" : "25",
      "Score" : "4/67.64",
      "Show" : "Nörten-Hardenberg",
      "StartDate" : "21/05/2016"
    },
    "21-07-2016,Gross Viegeln" : {
      "Article" : "238.2.1a",
      "Athlete" : "Lars NIEBERG (GER)",
      "Competition" : "Table A",
      "Event" : "CSIYH1*",
      "FEIID" : "10000416",
      "Obstheigh" : "135",
      "Pos" : "20",
      "Score" : "0/60.71",
      "Show" : "Gross Viegeln",
      "StartDate" : "21/07/2016"
    },
    "21-10-2017,Kronenberg" : {
      "Article" : "238.2.1a",
      "Athlete" : "Lars NIEBERG (GER)",
      "Competition" : "Table A",
      "Event" : "CSI2*",
      "FEIID" : "10000416",
      "Obstheigh" : "135",
      "Pos" : "11",
      "Score" : "0/63.88",
      "Show" : "Kronenberg",
      "StartDate" : "21/10/2017"
    },
    "22-01-2016,Schwerin" : {
      "Article" : "238.2.1a",
      "Athlete" : "Gerrit NIEBERG (GER)",
      "Competition" : "Table A",
      "Event" : "CSI1*",
      "FEIID" : "10046659",
      "Obstheigh" : "135",
      "Pos" : "37",
      "Score" : "5/54.30",
      "Show" : "Schwerin",
      "StartDate" : "22/01/2016"
    },
    "22-06-2018                                10_00,Riesenbeck" : {
      "Article" : "238.2.1a",
      "Athlete" : "Gerrit NIEBERG (GER)",
      "Competition" : "Table A",
      "Event" : "CSI2*",
      "FEIID" : "10046659",
      "Obstheigh" : "130",
      "Pos" : "59",
      "Score" : "12/91.45",
      "Show" : "Riesenbeck",
      "StartDate" : "22/06/2018                                10:00"
    },
    "22-07-2016,Gross Viegeln" : {
      "Article" : "238.2.1a",
      "Athlete" : "Lars NIEBERG (GER)",
      "Competition" : "Table A",
      "Event" : "CSIYH1*",
      "FEIID" : "10000416",
      "Obstheigh" : "135",
      "Pos" : "19",
      "Score" : "0/62.34",
      "Show" : "Gross Viegeln",
      "StartDate" : "22/07/2016"
    },
    "22-10-2017,Kronenberg" : {
      "Article" : "238.2.2a",
      "Athlete" : "Lars NIEBERG (GER)",
      "Competition" : "Table A",
      "Event" : "CSI2*",
      "FEIID" : "10000416",
      "Obstheigh" : "135",
      "Pos" : "24",
      "Score" : "1/67.49",
      "Show" : "Kronenberg",
      "StartDate" : "22/10/2017"
    },
    "23-02-2017,Damme-Neuenwalde" : {
      "Article" : "238.2.1a",
      "Athlete" : "Gerrit NIEBERG (GER)",
      "Competition" : "Table A",
      "Event" : "CSIYH1* incl. 8yo",
      "FEIID" : "10046659",
      "Obstheigh" : "130",
      "Pos" : "38",
      "Score" : "4/59.19",
      "Show" : "Damme-Neuenwalde",
      "StartDate" : "23/02/2017"
    },
    "23-02-2018,Kronenberg" : {
      "Article" : "274.5.3",
      "Athlete" : "Gerrit NIEBERG (GER)",
      "Competition" : "Two Phases",
      "Event" : "CSI2*",
      "FEIID" : "10046659",
      "Obstheigh" : "135",
      "Pos" : "20",
      "Score" : "0/51.51/0/33.29",
      "Show" : "Kronenberg",
      "StartDate" : "23/02/2018"
    },
    "23-03-2018,Dortmund" : {
      "Article" : "238.2.1a",
      "Athlete" : "Gerrit NIEBERG (GER)",
      "Competition" : "Competition 1",
      "Event" : "CSI4*",
      "FEIID" : "10046659",
      "Obstheigh" : "135",
      "Pos" : "12",
      "Score" : "0/50.77",
      "Show" : "Dortmund",
      "StartDate" : "23/03/2018"
    },
    "23-06-2017,Riesenbeck" : {
      "Article" : "238.2.1a",
      "Athlete" : "Gerrit NIEBERG (GER)",
      "Competition" : "Table A",
      "Event" : "CSI2*",
      "FEIID" : "10046659",
      "Obstheigh" : "130",
      "Pos" : "12",
      "Score" : "0/81.84",
      "Show" : "Riesenbeck",
      "StartDate" : "23/06/2017"
    },
    "23-06-2018                                09_00,Riesenbeck" : {
      "Article" : "274.5.3",
      "Athlete" : "Gerrit NIEBERG (GER)",
      "Competition" : "Two Phases",
      "Event" : "CSI2*",
      "FEIID" : "10046659",
      "Obstheigh" : "140",
      "Pos" : "11",
      "Score" : "0/51.55/0/40.09",
      "Show" : "Riesenbeck",
      "StartDate" : "23/06/2018                                09:00"
    },
    "23-11-2018,München" : {
      "Article" : "274.5.3",
      "Athlete" : "Gerrit NIEBERG (GER)",
      "Competition" : "Two Phases",
      "Event" : "CSI3*",
      "FEIID" : "10046659",
      "Obstheigh" : "145",
      "Pos" : "11",
      "Score" : "0/0/35.86",
      "Show" : "München",
      "StartDate" : "23/11/2018"
    },
    "24-02-2017,Damme-Neuenwalde" : {
      "Article" : "238.2.1a",
      "Athlete" : "Gerrit NIEBERG (GER)",
      "Competition" : "Table A",
      "Event" : "CSIYH1* incl. 8yo",
      "FEIID" : "10046659",
      "Obstheigh" : "135",
      "Pos" : "7",
      "Score" : "0/60.38",
      "Show" : "Damme-Neuenwalde",
      "StartDate" : "24/02/2017"
    },
    "24-02-2018,Kronenberg" : {
      "Article" : "238.2.1a",
      "Athlete" : "Gerrit NIEBERG (GER)",
      "Competition" : "Table A",
      "Event" : "CSI2*",
      "FEIID" : "10046659",
      "Obstheigh" : "135",
      "Pos" : "27",
      "Score" : "0/63.01",
      "Show" : "Kronenberg",
      "StartDate" : "24/02/2018"
    },
    "24-03-2018,Dortmund" : {
      "Article" : "238.2.1a",
      "Athlete" : "Gerrit NIEBERG (GER)",
      "Competition" : "Competition 2",
      "Event" : "CSI4*",
      "FEIID" : "10046659",
      "Obstheigh" : "140",
      "Pos" : "4",
      "Score" : "0/57.29",
      "Show" : "Dortmund",
      "StartDate" : "24/03/2018"
    },
    "24-05-2018,Uggerhalne" : {
      "Article" : "238.2.1a",
      "Athlete" : "Gerrit NIEBERG (GER)",
      "Competition" : "Table A",
      "Event" : "CSIO3*",
      "FEIID" : "10046659",
      "Obstheigh" : "140",
      "Pos" : "82",
      "Score" : "4/72.40",
      "Show" : "Uggerhalne",
      "StartDate" : "24/05/2018"
    },
    "24-06-2016,Kronenberg" : {
      "Article" : "274.5.3",
      "Athlete" : "Gerrit NIEBERG (GER)",
      "Competition" : "Two Phases",
      "Event" : "CSIYH1*",
      "FEIID" : "10046659",
      "Obstheigh" : "130-135",
      "Pos" : "7",
      "Score" : "0/60.40/0/30.44",
      "Show" : "Kronenberg",
      "StartDate" : "24/06/2016"
    },
    "24-06-2017,Riesenbeck" : {
      "Article" : "238.2.1a",
      "Athlete" : "Gerrit NIEBERG (GER)",
      "Competition" : "Table A",
      "Event" : "CSI2*",
      "FEIID" : "10046659",
      "Obstheigh" : "135",
      "Pos" : "10",
      "Score" : "0/75.88",
      "Show" : "Riesenbeck",
      "StartDate" : "24/06/2017"
    },
    "24-07-2016,Gross Viegeln" : {
      "Article" : "238.2.2a",
      "Athlete" : "Lars NIEBERG (GER)",
      "Competition" : "two phases",
      "Event" : "CSIYH1*",
      "FEIID" : "10000416",
      "Obstheigh" : "140",
      "Pos" : "37",
      "Score" : "4/58.02",
      "Show" : "Gross Viegeln",
      "StartDate" : "24/07/2016"
    },
    "24-08-2018,Münster" : {
      "Article" : "238.2.1a",
      "Athlete" : "Gerrit NIEBERG (GER)",
      "Competition" : "Table A",
      "Event" : "CSI4*",
      "FEIID" : "10046659",
      "Obstheigh" : "140",
      "Pos" : "14",
      "Score" : "0/82.18",
      "Show" : "Münster",
      "StartDate" : "24/08/2018"
    },
    "24-11-2018,München" : {
      "Article" : "269a",
      "Athlete" : "Gerrit NIEBERG (GER)",
      "Competition" : "Accumulator",
      "Event" : "CSI3*",
      "FEIID" : "10046659",
      "Obstheigh" : "145",
      "Pos" : "7",
      "Score" : "65/48.68",
      "Show" : "München",
      "StartDate" : "24/11/2018"
    },
    "25-01-2018,Kronenberg" : {
      "Article" : "238.2.1a",
      "Athlete" : "Lars NIEBERG (GER)",
      "Competition" : "Table A",
      "Event" : "CSI2*",
      "FEIID" : "10000416",
      "Obstheigh" : "140",
      "Pos" : "26",
      "Score" : "0/72.84",
      "Show" : "Kronenberg",
      "StartDate" : "25/01/2018"
    },
    "25-02-2017,Damme-Neuenwalde" : {
      "Article" : "274.5.6",
      "Athlete" : "Gerrit NIEBERG (GER)",
      "Competition" : "Two Phases",
      "Event" : "CSIYH1* incl. 8yo",
      "FEIID" : "10046659",
      "Obstheigh" : "135",
      "Pos" : "5",
      "Score" : "0/39.10/0/27.64",
      "Show" : "Damme-Neuenwalde",
      "StartDate" : "25/02/2017"
    },
    "25-02-2018,Kronenberg" : {
      "Article" : "238.2.2a",
      "Athlete" : "Gerrit NIEBERG (GER)",
      "Competition" : "Table A",
      "Event" : "CSI2*",
      "FEIID" : "10046659",
      "Obstheigh" : "135",
      "Pos" : "31",
      "Score" : "4/60.01",
      "Show" : "Kronenberg",
      "StartDate" : "25/02/2018"
    },
    "25-03-2014,Arezzo - Toscana Tour" : {
      "Article" : "238.1.1a",
      "Athlete" : "Dieter HAUCK (GER)",
      "Competition" : "Table A",
      "Event" : "CSIYH1*",
      "FEIID" : "10103664",
      "Obstheigh" : "115",
      "Pos" : "1",
      "Score" : "0",
      "Show" : "Arezzo - Toscana Tour",
      "StartDate" : "25/03/2014"
    },
    "25-03-2018,Dortmund" : {
      "Article" : "263",
      "Athlete" : "Gerrit NIEBERG (GER)",
      "Competition" : "Competition 5",
      "Event" : "CSI4*",
      "FEIID" : "10046659",
      "Obstheigh" : "145",
      "Pos" : "4",
      "Score" : "(0)/50.97",
      "Show" : "Dortmund",
      "StartDate" : "25/03/2018"
    },
    "25-05-2018,Uggerhalne" : {
      "Article" : "274.5.3",
      "Athlete" : "Gerrit NIEBERG (GER)",
      "Competition" : "Two Phases",
      "Event" : "CSIO3*",
      "FEIID" : "10046659",
      "Obstheigh" : "140",
      "Pos" : "81",
      "Score" : "4/50.68",
      "Show" : "Uggerhalne",
      "StartDate" : "25/05/2018"
    },
    "25-06-2017,Riesenbeck" : {
      "Article" : "274.5.3",
      "Athlete" : "Gerrit NIEBERG (GER)",
      "Competition" : "Two Phases",
      "Event" : "CSI2*",
      "FEIID" : "10046659",
      "Obstheigh" : "140",
      "Pos" : "6",
      "Score" : "0/0/40.61",
      "Show" : "Riesenbeck",
      "StartDate" : "25/06/2017"
    },
    "25-08-2018,Münster" : {
      "Article" : "274.5.3",
      "Athlete" : "Gerrit NIEBERG (GER)",
      "Competition" : "Two Phases",
      "Event" : "CSI4*",
      "FEIID" : "10046659",
      "Obstheigh" : "145",
      "Pos" : "14",
      "Score" : "0/0/36.55",
      "Show" : "Münster",
      "StartDate" : "25/08/2018"
    },
    "25-11-2016,Oldenburg" : {
      "Article" : "238.2.1a",
      "Athlete" : "Gerrit NIEBERG (GER)",
      "Competition" : "Table A",
      "Event" : "CSIYH1*",
      "FEIID" : "10046659",
      "Obstheigh" : "135",
      "Pos" : "36",
      "Score" : "4/60.84",
      "Show" : "Oldenburg",
      "StartDate" : "25/11/2016"
    },
    "26-01-2017,Kronenberg" : {
      "Article" : "238.2.1a",
      "Athlete" : "Gerrit NIEBERG (GER)",
      "Competition" : "Table A",
      "Event" : "CSI2*",
      "FEIID" : "10046659",
      "Obstheigh" : "140",
      "Pos" : "58",
      "Score" : "4/64.89",
      "Show" : "Kronenberg",
      "StartDate" : "26/01/2017"
    },
    "26-01-2018,Kronenberg" : {
      "Article" : "274.5.3",
      "Athlete" : "Lars NIEBERG (GER)",
      "Competition" : "Two Phases",
      "Event" : "CSI2*",
      "FEIID" : "10000416",
      "Obstheigh" : "140",
      "Pos" : "9",
      "Score" : "0/58.77/0/27.29",
      "Show" : "Kronenberg",
      "StartDate" : "26/01/2018"
    },
    "26-03-2014,Arezzo - Toscana Tour" : {
      "Article" : "238.1.1a",
      "Athlete" : "Dieter HAUCK (GER)",
      "Competition" : "Table A",
      "Event" : "CSIYH1*",
      "FEIID" : "10103664",
      "Obstheigh" : "115",
      "Pos" : "26",
      "Score" : "4",
      "Show" : "Arezzo - Toscana Tour",
      "StartDate" : "26/03/2014"
    },
    "26-06-2016,Kronenberg" : {
      "Article" : "238.2.2a",
      "Athlete" : "Gerrit NIEBERG (GER)",
      "Competition" : "Table A",
      "Event" : "CSIYH1*",
      "FEIID" : "10046659",
      "Obstheigh" : "130-135",
      "Pos" : "5",
      "Score" : "0/0/39.64",
      "Show" : "Kronenberg",
      "StartDate" : "26/06/2016"
    },
    "26-07-2018,Samorin" : {
      "Article" : "274.5.3",
      "Athlete" : "Gerrit NIEBERG (GER)",
      "Competition" : "Two Phases",
      "Event" : "CSI2*",
      "FEIID" : "10046659",
      "Obstheigh" : "145",
      "Pos" : "31",
      "Score" : "0/4/32.33",
      "Show" : "Samorin",
      "StartDate" : "26/07/2018"
    },
    "26-08-2016,Münster" : {
      "Article" : "238.2.1a",
      "Athlete" : "Gerrit NIEBERG (GER)",
      "Competition" : "Table A",
      "Event" : "CSIYH1* incl. 8yo",
      "FEIID" : "10046659",
      "Obstheigh" : "135",
      "Pos" : "32",
      "Score" : "1/76.23",
      "Show" : "Münster",
      "StartDate" : "26/08/2016"
    },
    "26-08-2018,Münster" : {
      "Article" : "238.2.2a",
      "Athlete" : "Gerrit NIEBERG (GER)",
      "Competition" : "Table A",
      "Event" : "CSI4*",
      "FEIID" : "10046659",
      "Obstheigh" : "150",
      "Pos" : "29",
      "Score" : "8/75.93",
      "Show" : "Münster",
      "StartDate" : "26/08/2018"
    },
    "27-01-2017,Kronenberg" : {
      "Article" : "274.5.3",
      "Athlete" : "Gerrit NIEBERG (GER)",
      "Competition" : "Two Phases",
      "Event" : "CSI2*",
      "FEIID" : "10046659",
      "Obstheigh" : "140",
      "Pos" : "49",
      "Score" : "4/56.45",
      "Show" : "Kronenberg",
      "StartDate" : "27/01/2017"
    },
    "27-01-2018,Kronenberg" : {
      "Article" : "238.2.2a",
      "Athlete" : "Lars NIEBERG (GER)",
      "Competition" : "Table A",
      "Event" : "CSI2*",
      "FEIID" : "10000416",
      "Obstheigh" : "140",
      "Pos" : "32",
      "Score" : "4/69.77",
      "Show" : "Kronenberg",
      "StartDate" : "27/01/2018"
    },
    "27-03-2014,Arezzo - Toscana Tour" : {
      "Article" : "274.5.1",
      "Athlete" : "Dieter HAUCK (GER)",
      "Competition" : "Two Phases",
      "Event" : "CSIYH1*",
      "FEIID" : "10103664",
      "Obstheigh" : "115",
      "Pos" : "23",
      "Score" : "0/4",
      "Show" : "Arezzo - Toscana Tour",
      "StartDate" : "27/03/2014"
    },
    "27-05-2018,Uggerhalne" : {
      "Article" : "238.2.1a",
      "Athlete" : "Gerrit NIEBERG (GER)",
      "Competition" : "Table A",
      "Event" : "CSIO3*",
      "FEIID" : "10046659",
      "Obstheigh" : "145",
      "Pos" : "36",
      "Score" : "8/79.51",
      "Show" : "Uggerhalne",
      "StartDate" : "27/05/2018"
    },
    "27-07-2018,Samorin" : {
      "Article" : "238.2.1a",
      "Athlete" : "Gerrit NIEBERG (GER)",
      "Competition" : "Table A",
      "Event" : "CSI2*",
      "FEIID" : "10046659",
      "Obstheigh" : "145",
      "Pos" : "21",
      "Score" : "4/68.41",
      "Show" : "Samorin",
      "StartDate" : "27/07/2018"
    },
    "27-08-2016,Münster" : {
      "Article" : "274.5.3",
      "Athlete" : "Gerrit NIEBERG (GER)",
      "Competition" : "Two Phases",
      "Event" : "CSIYH1* incl. 8yo",
      "FEIID" : "10046659",
      "Obstheigh" : "145-150",
      "Pos" : "21",
      "Score" : "4/40.06",
      "Show" : "Münster",
      "StartDate" : "27/08/2016"
    },
    "27-11-2016,Oldenburg" : {
      "Article" : "274.5.3",
      "Athlete" : "Gerrit NIEBERG (GER)",
      "Competition" : "Two Phases",
      "Event" : "CSIYH1*",
      "FEIID" : "10046659",
      "Obstheigh" : "140",
      "Pos" : "1",
      "Score" : "0/0/24.56",
      "Show" : "Oldenburg",
      "StartDate" : "27/11/2016"
    },
    "28-01-2017,Kronenberg" : {
      "Article" : "238.2.2a",
      "Athlete" : "Gerrit NIEBERG (GER)",
      "Competition" : "Table A",
      "Event" : "CSI2*",
      "FEIID" : "10046659",
      "Obstheigh" : "140",
      "Pos" : "RET",
      "Score" : "R1 RET",
      "Show" : "Kronenberg",
      "StartDate" : "28/01/2017"
    },
    "28-06-2018,Knokke" : {
      "Article" : "238.2.1a",
      "Athlete" : "Gerrit NIEBERG (GER)",
      "Competition" : "Table A",
      "Event" : "CSI3*",
      "FEIID" : "10046659",
      "Obstheigh" : "140",
      "Pos" : "16",
      "Score" : "0/74.74",
      "Show" : "Knokke",
      "StartDate" : "28/06/2018"
    },
    "28-07-2016,Ommen" : {
      "Article" : "238.2.1a",
      "Athlete" : "Gerrit NIEBERG (GER)",
      "Competition" : "Acon Afrasteringen Prijs",
      "Event" : "CSI1*",
      "FEIID" : "10046659",
      "Obstheigh" : "135",
      "Pos" : "16",
      "Score" : "0/61.55",
      "Show" : "Ommen",
      "StartDate" : "28/07/2016"
    },
    "28-07-2018,Samorin" : {
      "Article" : "273.4.3a-GP",
      "Athlete" : "Gerrit NIEBERG (GER)",
      "Competition" : "Grand Prix Two Rounds",
      "Event" : "CSI2*",
      "FEIID" : "10046659",
      "Obstheigh" : "145",
      "Pos" : "14",
      "Score" : "0/4/40.58",
      "Show" : "Samorin",
      "StartDate" : "28/07/2018"
    },
    "29-03-2016,Cagnes-sur-Mer" : {
      "Article" : "238.1.1a",
      "Athlete" : "Gerrit NIEBERG (GER)",
      "Competition" : "Table A - T A, one round not atc",
      "Event" : "CSIYH1*",
      "FEIID" : "10046659",
      "Obstheigh" : "105",
      "Pos" : "1",
      "Score" : "0/71.31",
      "Show" : "Cagnes-sur-Mer",
      "StartDate" : "29/03/2016"
    },
    "29-07-2016,Ommen" : {
      "Article" : "274.5.6",
      "Athlete" : "Gerrit NIEBERG (GER)",
      "Competition" : "Rabobank Vaart en Vechtstreek Prijs",
      "Event" : "CSI1*",
      "FEIID" : "10046659",
      "Obstheigh" : "135",
      "Pos" : "35",
      "Score" : "0/0.00/4/32.58",
      "Show" : "Ommen",
      "StartDate" : "29/07/2016"
    },
    "30-03-2016,Cagnes-sur-Mer" : {
      "Article" : "238.2.1a",
      "Athlete" : "Gerrit NIEBERG (GER)",
      "Competition" : "Table A - T A, one round atc",
      "Event" : "CSIYH1*",
      "FEIID" : "10046659",
      "Obstheigh" : "130",
      "Pos" : "57",
      "Score" : "8/91.61",
      "Show" : "Cagnes-sur-Mer",
      "StartDate" : "30/03/2016"
    },
    "30-06-2018,Knokke" : {
      "Article" : "238.2.2a",
      "Athlete" : "Gerrit NIEBERG (GER)",
      "Competition" : "Table A",
      "Event" : "CSI3*",
      "FEIID" : "10046659",
      "Obstheigh" : "140",
      "Pos" : "25",
      "Score" : "6/87.71",
      "Show" : "Knokke",
      "StartDate" : "30/06/2018"
    },
    "30-07-2015,Donaueschingen-Immenhöfe" : {
      "Article" : "238.2.1a",
      "Athlete" : "Gerrit NIEBERG (GER)",
      "Competition" : "Table A",
      "Event" : "CSIYH1*",
      "FEIID" : "10046659",
      "Obstheigh" : "130",
      "Pos" : "21",
      "Score" : "0/66.79",
      "Show" : "Donaueschingen-Immenhöfe",
      "StartDate" : "30/07/2015"
    },
    "31-03-2016,Cagnes-sur-Mer" : {
      "Article" : "238.2.2a",
      "Athlete" : "Gerrit NIEBERG (GER)",
      "Competition" : "Table A - T A, one round atc with one ju...",
      "Event" : "CSIYH1*",
      "FEIID" : "10046659",
      "Obstheigh" : "135",
      "Pos" : "33",
      "Score" : "4/94.76",
      "Show" : "Cagnes-sur-Mer",
      "StartDate" : "31/03/2016"
    },
    "31-07-2015,Donaueschingen-Immenhöfe" : {
      "Article" : "238.2.1a",
      "Athlete" : "Gerrit NIEBERG (GER)",
      "Competition" : "Table A",
      "Event" : "CSIYH1*",
      "FEIID" : "10046659",
      "Obstheigh" : "130-135",
      "Pos" : "27",
      "Score" : "1/70.60",
      "Show" : "Donaueschingen-Immenhöfe",
      "StartDate" : "31/07/2015"
    },
    "31-07-2016,Ommen" : {
      "Article" : "238.2.2a",
      "Athlete" : "Gerrit NIEBERG (GER)",
      "Competition" : "Stoeterij Sterrehof & Flybusters Prijs",
      "Event" : "CSI1*",
      "FEIID" : "10046659",
      "Obstheigh" : "135",
      "Pos" : "54",
      "Score" : "14/74.11",
      "Show" : "Ommen",
      "StartDate" : "31/07/2016"
    },
    "31-08-2016,Humlikon" : {
      "Article" : "238.2.2a",
      "Athlete" : "Gerrit NIEBERG (GER)",
      "Competition" : "Int. Jumping Competition with jo Preis d...",
      "Event" : "CSI3*",
      "FEIID" : "10046659",
      "Obstheigh" : "130",
      "Pos" : "7",
      "Score" : "0/0/35.70",
      "Show" : "Humlikon",
      "StartDate" : "31/08/2016"
    }
  },
  "Complete_Name" : "",
  "Country_of_Birth" : "Germany",
  "Current_Name" : "BACCORD",
  "Dam" : "Ila II ",
  "Dams_UELN" : "276321210238294",
  "Date Of birth" : "01/05/2009 (9 y)",
  "Date_of_Death" : "",
  "Date_of_Retirement" : "",
  "FEIID" : "104FW21",
  "FEI_Recognized" : "DE 418180071009",
  "Gender" : "Male",
  "Height_cm" : " ",
  "ID_Type" : "Recognition card",
  "Issuing_Body" : "GER - Springpferdezuchtverband Oldenburg-International e.V.",
  "Issuing_Date" : "27/03/2014",
  "Issuing_NF" : "GER",
  "Name" : "BACCORD",
  "National_ID" : "DE 418180071009",
  "PI" : 600,
  "Pony" : "No",
  "Registration" : "S S19",
  "Sex" : "Gelding",
  "Shorten_Name" : "",
  "Sire" : "BALOU DU ROUET",
  "Sire_of_Dam" : "ACORD II",
  "Sires_UELN" : " 276321210002687",
  "Status" : "Active",
  "Studbook" : "OS - Springpferdezuchtverband Oldenburg-International e.V",
  "Type" : "RC",
  "UELN" : "276418180071009",
  "Valid_Until" : "03/05/2022History..."
}
}
